spatial_data/__init__.py
spatial_data/base_logger.py
spatial_data/constants.py
spatial_data/container.py
spatial_data/la/__init__.py
spatial_data/la/label.py
spatial_data/pl/__init__.py
spatial_data/pl/cmap.py
spatial_data/pl/plot.py
spatial_data/pl/spectra.py
spatial_data/pp/__init__.py
spatial_data/pp/image.py
spatial_data/pp/segmentation.py
spatial_data/pp/transforms.py
spatial_data/se/__init__.py
spatial_data/se/helper.py
spatial_data/se/segmentation.py
spat_data-0.3.0.dist-info/LICENSE
spat_data-0.3.0.dist-info/WHEEL
spat_data-0.3.0.dist-info/METADATA
spat_data-0.3.0.dist-info/RECORD
